<?xml version="1.0" encoding="UTF-8"?>
<checkstyle version="6.11.2">
<file name="C:\Users\taylo_000\Downloads\Hangman\Hangman.java">
</file>
<file name="C:\Users\taylo_000\Downloads\Hangman\HangmanConsole.java">
<error line="0" severity="error" message="File does not end with a newline." source="com.puppycrawl.tools.checkstyle.checks.NewlineAtEndOfFileCheck"/>
</file>
<file name="C:\Users\taylo_000\Downloads\Hangman\HangmanGUI.java">
<error line="0" severity="error" message="File does not end with a newline." source="com.puppycrawl.tools.checkstyle.checks.NewlineAtEndOfFileCheck"/>
<error line="92" severity="error" message="Line has trailing spaces." source="com.puppycrawl.tools.checkstyle.checks.regexp.RegexpSinglelineCheck"/>
<error line="131" column="31" severity="error" message="&apos;{&apos; at column 31 should have line break after." source="com.puppycrawl.tools.checkstyle.checks.blocks.LeftCurlyCheck"/>
</file>
<file name="C:\Users\taylo_000\Downloads\Hangman\HangmanManager.java">
<error line="0" severity="error" message="File does not end with a newline." source="com.puppycrawl.tools.checkstyle.checks.NewlineAtEndOfFileCheck"/>
<error line="22" severity="error" message="Line is longer than 80 characters (found 82)." source="com.puppycrawl.tools.checkstyle.checks.sizes.LineLengthCheck"/>
</file>
</checkstyle>
